LICENSE
MANIFEST.in
README.md
index.html
setup.cfg
setup.py
docs/index.rst
docs/main.rst
grail/__init__.py
grail/base_test.py
grail/settings.py
grail/state.py
grail/step_info.py
grail/steps.py
grail.egg-info/PKG-INFO
grail.egg-info/SOURCES.txt
grail.egg-info/dependency_links.txt
grail.egg-info/top_level.txt