Metadata-Version: 1.1
Name: grail
Version: 1.0.9
Summary: Grail is a library which allows test script creation based on steps. It helps to structure your tests and get rid of additional test documentation for your code.
Home-page: https://github.com/wgnet/grail
Author: Wargaming.NET
Author-email: web_qa_auto@wargaming.net
License: UNKNOWN
Platform: UNKNOWN
Classifier: Intended Audience :: Developers
Classifier: Operating System :: OS Independent
Classifier: Programming Language :: Python
Classifier: Programming Language :: Python :: 2.6
Classifier: Programming Language :: Python :: 2.7
